metapg/pool/__init__.py
metapg/pool/config.py
metapg/pool/cursor.py
metapg/pool/events.py
metapg/pool/pool.py
metapg/pool/py.typed
metapg_pool-0.3.1.dist-info/METADATA
metapg_pool-0.3.1.dist-info/WHEEL
metapg_pool-0.3.1.dist-info/RECORD
